jarvis.py
app/__init__.py
app/__main__.py
app/models/__init__.py
app/models/bot.py
app/models/chat.py
app/utils/__init__.py
app/utils/cache.py
app/utils/consts.py
app/utils/env.py
app/utils/print.py
app/utils/validation.py
jarvis_chat_cli-0.1.5.dist-info/LICENSE
jarvis_chat_cli-0.1.5.dist-info/METADATA
jarvis_chat_cli-0.1.5.dist-info/WHEEL
jarvis_chat_cli-0.1.5.dist-info/entry_points.txt
jarvis_chat_cli-0.1.5.dist-info/top_level.txt
jarvis_chat_cli-0.1.5.dist-info/RECORD
